nonebot_plugin_groupAccountant/__init__.py
nonebot_plugin_groupAccountant/acountant.py
nonebot_plugin_groupaccountant-0.0.2.dist-info/LICENSE
nonebot_plugin_groupaccountant-0.0.2.dist-info/METADATA
nonebot_plugin_groupaccountant-0.0.2.dist-info/WHEEL
nonebot_plugin_groupaccountant-0.0.2.dist-info/RECORD
