Metadata-Version: 2.1
Name: nonebot_plugin_groupAccountant
Version: 0.0.2
Summary: A group chat accountant for nonebot
Home-page: https://github.com/shilapi/nonebot-plugin-groupAccountant
License: MIT
Author: shilapi
Author-email: shilapi@outlook.com
Requires-Python: >=3.10.6,<4.0.0
Classifier: License :: OSI Approved :: MIT License
Classifier: Programming Language :: Python :: 3
Classifier: Programming Language :: Python :: 3.11
Requires-Dist: nonebot-adapter-onebot (>=2.2.4,<3.0.0)
Requires-Dist: nonebot2 (>=2.0.1,<3.0.0)
Requires-Dist: nonebot_plugin_localstore (>=0.5.0,<0.6.0)
Project-URL: Repository, https://github.com/shilapi/nonebot-plugin-groupAccountant
